Workbook
Name \w: #REF!
Name \z: #REF!
Name _1990: #REF!
Name _PAS1990: #REF!
Name _PYG1990: #REF!
Name _PYG1999: [2]RESULTADOS!$O$1:$R$63
Name BALANCE: #REF!
Name ESF.ACTUAL: '2.ESF'!$E$75
Name ESF.PREVIO: '2.ESF'!$F$75
Name FLUJO.ACTUAL: '[1]5.FLUJO DE EFECTIVO'!$G$100
Name FLUJO.PREVIO: '[1]5.FLUJO DE EFECTIVO'!$H$100
Name PAT.ACTUAL: '[1]4.CAMBIOS EN EL PAT'!$M$29
Name PAT.PREVIO: '[1]4.CAMBIOS EN EL PAT'!$M$20
Name PYG: #REF!

Sheet 2.ESF
K2: jul
C3: ESTADOS FINANCIEROS INDIVIDUALES | J3: MES | K3: jul
C4: ESTADO DE SITUACIÓN FINANCIERA | J4: AÑO FINAL | K4: 2024
C5: Por el período terminados al 31 de julio de 2026 y 2025 | J5: AÑO INICIAL | K5: 2024
C7: =+'[1]1.CERTIFICACIÓN'!A6 -> OFTALMOLOGOS EL TESORO S.A.S
E9: 2026 | F9: 2025
D10: Notas | E10: Julio 2026 | F10: Julio 2025 | G10: $ Var | H10: % Var
C12: ACTIVO
C13: Activo corriente
A14: 11 | C14: Efectivo y equivalentes al efectivo | D14: 5 | E14: =+IFERROR((VLOOKUP((CONCATENATE($K$3,$E$9,$A14)),'[1]AÑO 2026'!$D:$I,6,0)),0) -> -4214553.1 | F14: =+IFERROR((VLOOKUP((CONCATENATE($K$3,$F$9,$A14)),'[1]AÑO 2025'!$D:$I,6,0)),0) -> 9.5596683e+08 | G14: =+E14-F14 -> -9.6018138e+08 | H14: =IFERROR(G14/F14,0) -> -1.0044087
A15: 12 | C15: Inversiones | E15: =+IFERROR((VLOOKUP((CONCATENATE($K$3,$E$9,$A15)),'[1]AÑO 2026'!$D:$I,6,0)),0) -> 0 | F15: =+IFERROR((VLOOKUP((CONCATENATE($K$3,$F$9,$A15)),'[1]AÑO 2025'!$D:$I,6,0)),0) -> 0 | G15: =+E15-F15 -> 0 | H15: =IFERROR(G15/F15,0) -> 0
A16: 13 | C16: Cuentas comerciales por cobrar y otras cuentas por cobrar | D16: 6 | E16: =+IFERROR((VLOOKUP((CONCATENATE($K$3,$E$9,$A16)),'[1]AÑO 2026'!$D:$I,6,0)),0) -> 2.7736917e+09 | F16: =+IFERROR((VLOOKUP((CONCATENATE($K$3,$F$9,$A16)),'[1]AÑO 2025'!$D:$I,6,0)),0) -> 1.3450386e+09 | G16: =+E16-F16 -> 1.4286531e+09 | H16: =IFERROR(G16/F16,0) -> 1.0621652
A17: 14 | C17: Inventarios | E17: =+IFERROR((VLOOKUP((CONCATENATE($K$3,$E$9,$A17)),'[1]AÑO 2026'!$D:$I,6,0)),0) -> 568990212 | F17: =+IFERROR((VLOOKUP((CONCATENATE($K$3,#REF!,$A17)),'[1]AÑO 2025'!$D:$I,6,0)),0) -> 0 | G17: =+E17-F17 -> 568990212 | H17: =IFERROR(G17/F17,0) -> 0
C18: Total activo corriente | E18: =+SUM(E14:E17) -> 3.3384673e+09 | F18: =+SUM(F14:F17) -> 2.3010054e+09 | G18: =SUM(G14:G17) -> 1.037462e+09 | H18: =IFERROR(G18/F18,0) -> 0.45087332
C19: Activos no corriente | H19: =IFERROR(G19/F19,0) -> 0
A20: 15 | C20: Propiedad, planta y equipo | D20: 7 | E20: =+IFERROR((VLOOKUP((CONCATENATE($K$3,$E$9,$A20)),'[1]AÑO 2026'!$D:$I,6,0)),0) -> 1.0046736e+10 | F20: =+IFERROR((VLOOKUP((CONCATENATE($K$3,$F$9,$A20)),'[1]AÑO 2025'!$D:$I,6,0)),0) -> 6.6617245e+09 | G20: =+E20-F20 -> 3.385011e+09 | H20: =IFERROR(G20/F20,0) -> 0.50812834
A21: 16 | C21: Activos intangibles | E21: =+IFERROR((VLOOKUP((CONCATENATE($K$3,$E$9,$A21)),'[1]AÑO 2026'!$D:$I,6,0)),0) -> 0 | F21: =+IFERROR((VLOOKUP((CONCATENATE($K$3,$F$9,$A21)),'[1]AÑO 2025'!$D:$I,6,0)),0) -> 0 | G21: =+E21-F21 -> 0 | H21: =IFERROR(G21/F21,0) -> 0
A22: 17 | C22: Activos diferidos | D22: 8 | E22: =+IFERROR((VLOOKUP((CONCATENATE($K$3,$E$9,$A22)),'[1]AÑO 2026'!$D:$I,6,0)),0) -> 2.7186446e+08 | F22: =+IFERROR((VLOOKUP((CONCATENATE($K$3,$F$9,$A22)),'[1]AÑO 2025'!$D:$I,6,0)),0) -> 118964993 | G22: =+E22-F22 -> 1.5289947e+08 | H22: =IFERROR(G22/F22,0) -> 1.2852476
A23: 18 | C23: Otros activos | E23: =+IFERROR((VLOOKUP((CONCATENATE($K$3,$E$9,$A23)),'[1]AÑO 2026'!$D:$I,6,0)),0) -> 0 | F23: =+IFERROR((VLOOKUP((CONCATENATE($K$3,$F$9,$A23)),'[1]AÑO 2025'!$D:$I,6,0)),0) -> 0 | G23: =+E23-F23 -> 0 | H23: =IFERROR(G23/F23,0) -> 0
A24: 19 | C24: Activo por impuesto diferido | E24: =+IFERROR((VLOOKUP((CONCATENATE($K$3,$E$9,$A24)),'[1]AÑO 2026'!$D:$I,6,0)),0) -> 0 | F24: =+IFERROR((VLOOKUP((CONCATENATE($K$3,$F$9,$A24)),'[1]AÑO 2025'!$D:$I,6,0)),0) -> 0 | G24: =+E24-F24 -> 0 | H24: =IFERROR(G24/F24,0) -> 0
C25: Total activo no corriente | E25: =+SUM(E20:E24) -> 1.03186e+10 | F25: =+SUM(F20:F24) -> 6.7806895e+09 | G25: =SUM(G20:G24) -> 3.5379105e+09 | H25: =IFERROR(G25/F25,0) -> 0.52176264
C26: TOTAL ACTIVOS | E26: =+E18+E25 -> 1.3657067e+10 | F26: =+F18+F25 -> 9.0816949e+09 | G26: =+E26-F26 -> 4.5753724e+09 | H26: =IFERROR(G26/F26,0) -> 0.5038016
C27: PASIVO
C28: Pasivo corriente | H28: =IFERROR(G28/F28,0) -> 0
A29: 2105 | C29: Obligaciones financieras | D29: 9 | E29: =+IFERROR((VLOOKUP((CONCATENATE($K$3,$E$9,$A29)),'[1]AÑO 2026'!$D:$I,6,0)),0) -> -5.6887498e+08 | F29: =+IFERROR((VLOOKUP((CONCATENATE($K$3,$F$9,$A29)),'[1]AÑO 2025'!$D:$I,6,0)),0) -> -6.2439718e+08 | G29: =+E29-F29 -> 55522206 | H29: =IFERROR(G29/F29,0) -> -0.088921294 | J29: ESTE VALOR ES MANUAL
A30: 22050501 | C30: Cuentas por pagar a proveedores | D30: 10 | E30: =+IFERROR((VLOOKUP((CONCATENATE($K$3,$E$9,$A30)),'[1]AÑO 2026'!$D:$I,6,0)),0) -> -3.0635048e+09 | F30: =+IFERROR((VLOOKUP((CONCATENATE($K$3,$F$9,$A30)),'[1]AÑO 2025'!$D:$I,6,0)),0) -> -1.5435094e+09 | G30: =+E30-F30 -> -1.5199954e+09 | H30: =IFERROR(G30/F30,0) -> 0.98476594
A31: 23 | C31: Cuentas comerciales por pagar y otras cuentas por pagar | D31: 11 | E31: =+IFERROR((VLOOKUP((CONCATENATE($K$3,$E$9,$A31)),'[1]AÑO 2026'!$D:$I,6,0)),0) -> -3.9087047e+08 | F31: =+IFERROR((VLOOKUP((CONCATENATE($K$3,$F$9,$A31)),'[1]AÑO 2025'!$D:$I,6,0)),0) -> -2.5971036e+08 | G31: =+E31-F31 -> -1.3116011e+08 | H31: =IFERROR(G31/F31,0) -> 0.50502456
A32: 24 | C32: Impuestos, gravámenes y tasas | E32: =+IFERROR((VLOOKUP((CONCATENATE($K$3,$E$9,$A32)),'[1]AÑO 2026'!$D:$I,6,0)),0) -> -394074690 | F32: =+IFERROR((VLOOKUP((CONCATENATE($K$3,$F$9,$A32)),'[1]AÑO 2025'!$D:$I,6,0)),0) -> 0 | G32: =+E32-F32 -> -394074690 | H32: =IFERROR(G32/F32,0) -> 0
A33: 25 | C33: Pasivo por beneficios a empleados | D33: 12 | E33: =+IFERROR((VLOOKUP((CONCATENATE($K$3,$E$9,$A33)),'[1]AÑO 2026'!$D:$I,6,0)),0) -> -2.7187872e+08 | F33: =+IFERROR((VLOOKUP((CONCATENATE($K$3,$F$9,$A33)),'[1]AÑO 2025'!$D:$I,6,0)),0) -> -1.0749475e+08 | G33: =+E33-F33 -> -1.6438397e+08 | H33: =IFERROR(G33/F33,0) -> 1.5292278
A34: 26 | C34: Pasivos estimados y provisiones | E34: =+IFERROR((VLOOKUP((CONCATENATE($K$3,$E$9,$A34)),'[1]AÑO 2026'!$D:$I,6,0)),0) -> 0 | F34: =+IFERROR((VLOOKUP((CONCATENATE($K$3,$F$9,$A34)),'[1]AÑO 2025'!$D:$I,6,0)),0) -> 0 | G34: =+E34-F34 -> 0 | H34: =IFERROR(G34/F34,0) -> 0
A35: 28 | C35: Anticipos recibidos | D35: 13 | E35: =+IFERROR((VLOOKUP((CONCATENATE($K$3,$E$9,$A35)),'[1]AÑO 2026'!$D:$I,6,0)),0) -> -6.8779381e+08 | F35: =+IFERROR((VLOOKUP((CONCATENATE($K$3,$F$9,$A35)),'[1]AÑO 2025'!$D:$I,6,0)),0) -> -2.7143938e+09 | G35: =+E35-F35 -> 2.0266e+09 | H35: =IFERROR(G35/F35,0) -> -0.74661237
C36: Total pasivo corriente | E36: =+SUM(E29:E35) -> -5.3769975e+09 | F36: =+SUM(F29:F35) -> -5.2495055e+09 | G36: =+E36-F36 -> -1.2749199e+08 | H36: =IFERROR(G36/F36,0) -> 0.024286476
C37: Pasivo no corriente | H37: =IFERROR(G37/F37,0) -> 0
A38: 2115 | C38: Obligaciones financieras | D38: 9 | E38: =+IFERROR((VLOOKUP((CONCATENATE($K$3,$E$9,$A38)),'[1]AÑO 2026'!$D:$I,6,0)),0) -> -1.6251785e+08 | F38: =+IFERROR((VLOOKUP((CONCATENATE($K$3,$F$9,$A38)),'[1]AÑO 2025'!$D:$I,6,0)),0) -> -56922180 | G38: =+E38-F38 -> -1.0559567e+08 | H38: =IFERROR(G38/F38,0) -> 1.8550883
A39: 22050502 | C39: Cuentas por pagar a proveedores | D39: 10 | E39: =+IFERROR((VLOOKUP((CONCATENATE($K$3,$E$9,$A39)),'[1]AÑO 2026'!$D:$I,6,0)),0) -> -1710110688 | F39: =+IFERROR((VLOOKUP((CONCATENATE($K$3,$F$9,$A39)),'[1]AÑO 2025'!$D:$I,6,0)),0) -> -1051598275 | G39: =+E39-F39 -> -658512413 | H39: =IFERROR(G39/F39,0) -> 0.6262015
A40: 23 | C40: Cuentas comerciales por pagar y otras cuentas por pagar
A41: 29 | C41: Pasivo por impuesto diferido | D41: 14 | E41: =+IFERROR((VLOOKUP((CONCATENATE($K$3,$E$9,$A41)),'[1]AÑO 2026'!$D:$I,6,0)),0) -> -80203562 | F41: =+IFERROR((VLOOKUP((CONCATENATE($K$3,$F$9,$A41)),'[1]AÑO 2025'!$D:$I,6,0)),0) -> -80203562 | G41: =+E41-F41 -> 0 | H41: =IFERROR(G41/F41,0) -> 0
C42: Total pasivo no corriente | E42: =SUM(E38:E41) -> -1.9528321e+09 | F42: =SUM(F38:F41) -> -1.188724e+09 | G42: =+E42-F42 -> -7.6410808e+08 | H42: =IFERROR(G42/F42,0) -> 0.64279687
C43: TOTAL PASIVOS | E43: =+E36+E42 -> -7.3298296e+09 | F43: =+F36+F42 -> -6.4382295e+09 | G43: =+E43-F43 -> -8.9160007e+08 | H43: =IFERROR(G43/F43,0) -> 0.13848529
C44: PATRIMONIO
A45: 31 | C45: Capital emitido | D45: 15 | E45: =+IFERROR((VLOOKUP((CONCATENATE($K$3,$E$9,$A45)),'[1]AÑO 2026'!$D:$I,6,0)),0) -> -5115500000 | F45: =+IFERROR((VLOOKUP((CONCATENATE($K$3,$F$9,$A45)),'[1]AÑO 2025'!$D:$I,6,0)),0) -> -1200500000 | G45: =+E45-F45 -> -3915000000 | H45: =IFERROR(G45/F45,0) -> 3.2611412
A46: 32 | C46: Prima en emisión de capital | D46: 15 | E46: =+IFERROR((VLOOKUP((CONCATENATE($K$3,$E$9,$A46)),'[1]AÑO 2026'!$D:$I,6,0)),0) -> -3.8878472e+08 | F46: =+IFERROR((VLOOKUP((CONCATENATE($K$3,$F$9,$A46)),'[1]AÑO 2025'!$D:$I,6,0)),0) -> -3.8878472e+08 | G46: =+E46-F46 -> 0 | H46: =IFERROR(G46/F46,0) -> 0
A47: 36 | C47: Utilidades del ejercicios en cuentas en participación | D47: 15 | E47: =+IFERROR((VLOOKUP((CONCATENATE($K$3,$E$9,$A47)),'[1]AÑO 2026'!$D:$I,6,0)),0) -> 0 | F47: =+IFERROR((VLOOKUP((CONCATENATE($K$3,$F$9,$A47)),'[1]AÑO 2025'!$D:$I,6,0)),0) -> -16898975 | G47: =+E47-F47 -> 16898975 | H47: =IFERROR(G47/F47,0) -> -1
A48: 37 | C48: Resultados acumulados | D48: 15 | E48: =+IFERROR((VLOOKUP((CONCATENATE($K$3,$E$9,$A48)),'[1]AÑO 2026'!$D:$I,6,0)),0) -> -7.33069e+08 | F48: =+IFERROR((VLOOKUP((CONCATENATE($K$3,$F$9,$A48)),'[1]AÑO 2025'!$D:$I,6,0)),0) -> -2.4233647e+08 | G48: =+E48-F48 -> -4.9073253e+08 | H48: =IFERROR(G48/F48,0) -> 2.0250049
A49: 38 | C49: Ajustes por adopción NIIF | D49: 15 | E49: =+IFERROR((VLOOKUP((CONCATENATE($K$3,$E$9,$A49)),'[1]AÑO 2026'!$D:$I,6,0)),0) -> 0 | F49: =+IFERROR((VLOOKUP((CONCATENATE($K$3,$F$9,$A49)),'[1]AÑO 2025'!$D:$I,6,0)),0) -> 0 | G49: =+E49-F49 -> 0 | H49: =IFERROR(G49/F49,0) -> 0
C50: Resultado Del Ejercicio | D50: 15 | E50: =-'3.ERI'!E70 -> -89884071 | F50: =-'3.ERI'!F70 -> -7.9494526e+08 | G50: =+E50-F50 -> 7.0506119e+08 | H50: =IFERROR(G50/F50,0) -> -0.88693049
C51: TOTAL PATRIMONIO | E51: =SUM(E45:E50) -> -6.3272378e+09 | F51: =SUM(F45:F50) -> -2.6434654e+09 | G51: =SUM(G45:G50) -> -3.6837724e+09 | H51: =IFERROR(G51/F51,0) -> 1.3935391
C52: TOTAL PASIVO Y PATRIMONIO | E52: =+E43+E51 -> -1.3657067e+10 | F52: =+F43+F51 -> -9.0816949e+09 | G52: =+G43+G51 -> -4.5753724e+09 | H52: =IFERROR(G52/F52,0) -> 0.5038016
C53: Las notas son parte integral de los estados financieros individuales
C59: =+'[1]1.CERTIFICACIÓN'!A45 -> MIGUEL ANTONIO JARAMILLO M | D59: ELIZABETH SOTO MEJIA | G59: =+'[1]1.CERTIFICACIÓN'!C45 -> YURANY DEOSSA MURILLO
C60: =+'[1]1.CERTIFICACIÓN'!A46 -> Representante Legal | D60: Revisor Fiscal | G60: =+'[1]1.CERTIFICACIÓN'!C46 -> Contador Público
C61: =+'[1]1.CERTIFICACIÓN'!A47 -> CC 80.550.424 | D61: Designado por TAX CONTADORES Y ABOGADOS S.A.S | G61: =+'[1]1.CERTIFICACIÓN'!C47 -> TP 265026-T
C62: (Ver Certificación Adjunta) | D62: TP 265041-T | G62: (Ver Certificación Adjunta)
D63: (Ver Opinión Adjunta)
C75: VERIFICACIÓN: | E75: =+E26+E52 -> 0 | F75: =+F26+F52 -> 0
C76: ECUACIÓN PATRIMONIAL | E76: =+E26-E52 -> 2.7314135e+10 | F76: =+F26-F52 -> 1.816339e+10

Sheet 3.ERI
K2: jul
C3: =+'2.ESF'!C3 -> ESTADOS FINANCIEROS INDIVIDUALES | J3: MES | K3: feb
C4: ESTADO DE RESULTADOS INTEGRAL | K4: 2024
C5: Por el período terminados al 31 de julio de 2026 y 2025
C7: =+'2.ESF'!C7 -> OFTALMOLOGOS EL TESORO S.A.S
E9: 2026 | F9: 2025
D10: Notas | E10: Julio 2026 | F10: Julio 2025 | G10: $ Var | H10: % Var
C12: INGRESOS OPERACIONALES
A13: 41 | C13: =PROPER(+IFERROR(VLOOKUP(A13,'[1]AÑO 2025'!C:I,3,FALSE),0)) -> Ingresos Ordinarios | D13: 16 | E13: =+IFERROR((VLOOKUP((CONCATENATE($K$2,$E$9,$A13)),'[1]AÑO 2026'!$D:$I,6,0)),0)*-1 -> 10629413901 | F13: =+IFERROR((VLOOKUP((CONCATENATE($K$2,$F$9,$A13)),'[1]AÑO 2025'!$D:$I,6,0)),0)*-1 -> 7.8475806e+09 | G13: =+E13-F13 -> 2.7818333e+09 | H13: =IFERROR(G13/F13,0) -> 0.35448292
A14: 6 | C14: =PROPER(+IFERROR(VLOOKUP(A14,'[1]AÑO 2025'!C:I,3,FALSE),0)) -> Costo De Ventas Y Prestación De Servicios | E14: =+IFERROR((VLOOKUP((CONCATENATE($K$2,$E$9,$A14)),'[1]AÑO 2026'!$D:$I,6,0)),0)*-1 -> -6.0044849e+09 | F14: =+IFERROR((VLOOKUP((CONCATENATE($K$2,$F$9,$A14)),'[1]AÑO 2025'!$D:$I,6,0)),0)*-1 -> -4.3795629e+09 | G14: =+E14-F14 -> -1.6249219e+09 | H14: =IFERROR(G14/F14,0) -> 0.37102376
A15: 7 | C15: =PROPER(+IFERROR(VLOOKUP(A15,'[1]AÑO 2025'!C:I,3,FALSE),0)) -> Costos De Producción | E15: =+IFERROR((VLOOKUP((CONCATENATE($K$2,$E$9,$A15)),'[1]AÑO 2026'!$D:$I,6,0)),0)*-1 -> -660802687 | F15: =+IFERROR((VLOOKUP((CONCATENATE($K$2,$F$9,$A15)),'[1]AÑO 2025'!$D:$I,6,0)),0)*-1 -> -2.3449977e+08 | G15: =+E15-F15 -> -4.2630291e+08 | H15: =IFERROR(G15/F15,0) -> 1.8179246
C16: Utilidad Bruta | E16: =+SUM(E13:E15) -> 3.9641263e+09 | F16: =+SUM(F13:F15) -> 3.2335179e+09 | G16: =+E16-F16 -> 7.3060847e+08 | H16: =IFERROR(G16/F16,0) -> 0.22594849
E17: =+E16/E13 -> 0.37293932 | F17: =+F16/F13 -> 0.4120401 | G17: =+E17-F17 -> -0.039100782 | H17: =+F17-G17 -> 0.45114088
C18: GASTROS ADMINISTRATIVOS
A19: 5105 | C19: =PROPER(+IFERROR(VLOOKUP(A19,'[1]AÑO 2025'!C:I,3,FALSE),0)) -> Gasto De Personal | D19: 17 | E19: =+IFERROR((VLOOKUP((CONCATENATE($K$2,$E$9,$A19)),'[1]AÑO 2026'!$D:$I,6,0)),0)*-1 -> -1.0444162e+09 | F19: =+IFERROR((VLOOKUP((CONCATENATE($K$2,$F$9,$A19)),'[1]AÑO 2025'!$D:$I,6,0)),0)*-1 -> -7.5852333e+08 | G19: =+E19-F19 -> -2.8589285e+08 | H19: =IFERROR(G19/F19,0) -> 0.37690713
A20: 5110 | C20: =PROPER(+IFERROR(VLOOKUP(A20,'[1]AÑO 2025'!C:I,3,FALSE),0)) -> Gastos Honorarios Administración | D20: 17 | E20: =+IFERROR((VLOOKUP((CONCATENATE($K$2,$E$9,$A20)),'[1]AÑO 2026'!$D:$I,6,0)),0)*-1 -> -1.9991019e+08 | F20: =+IFERROR((VLOOKUP((CONCATENATE($K$2,$F$9,$A20)),'[1]AÑO 2025'!$D:$I,6,0)),0)*-1 -> -1.4692011e+08 | G20: =+E20-F20 -> -52990074 | H20: =IFERROR(G20/F20,0) -> 0.36067269
A21: 5115 | C21: =PROPER(+IFERROR(VLOOKUP(A21,'[1]AÑO 2025'!C:I,3,FALSE),0)) -> Gastos Impuestos Administración | D21: 17 | E21: =+IFERROR((VLOOKUP((CONCATENATE($K$2,$E$9,$A21)),'[1]AÑO 2026'!$D:$I,6,0)),0)*-1 -> -49539473 | F21: =+IFERROR((VLOOKUP((CONCATENATE($K$2,$F$9,$A21)),'[1]AÑO 2025'!$D:$I,6,0)),0)*-1 -> -45445510 | G21: =+E21-F21 -> -4093963.4 | H21: =IFERROR(G21/F21,0) -> 0.090085102
A22: 5120 | C22: =PROPER(+IFERROR(VLOOKUP(A22,'[1]AÑO 2025'!C:I,3,FALSE),0)) -> Gastos Arrendamientos Administración | D22: 17 | E22: =+IFERROR((VLOOKUP((CONCATENATE($K$2,$E$9,$A22)),'[1]AÑO 2026'!$D:$I,6,0)),0)*-1 -> -7.416161e+08 | F22: =+IFERROR((VLOOKUP((CONCATENATE($K$2,$F$9,$A22)),'[1]AÑO 2025'!$D:$I,6,0)),0)*-1 -> -5.0376043e+08 | G22: =+E22-F22 -> -2.3785567e+08 | H22: =IFERROR(G22/F22,0) -> 0.47216028
A23: 5125 | C23: =PROPER(+IFERROR(VLOOKUP(A23,'[1]AÑO 2025'!C:I,3,FALSE),0)) -> Gastos Contribuciones Y Afiliaciones Administración | D23: 17 | E23: =+IFERROR((VLOOKUP((CONCATENATE($K$2,$E$9,$A23)),'[1]AÑO 2026'!$D:$I,6,0)),0)*-1 -> -1.2001923e+08 | F23: =+IFERROR((VLOOKUP((CONCATENATE($K$2,$F$9,$A23)),'[1]AÑO 2025'!$D:$I,6,0)),0)*-1 -> -91984229 | G23: =+E23-F23 -> -28034999 | H23: =IFERROR(G23/F23,0) -> 0.3047805
A24: 5130 | C24: =PROPER(+IFERROR(VLOOKUP(A24,'[1]AÑO 2025'!C:I,3,FALSE),0)) -> Gastos Seguros Administración | D24: 17 | E24: =+IFERROR((VLOOKUP((CONCATENATE($K$2,$E$9,$A24)),'[1]AÑO 2026'!$D:$I,6,0)),0)*-1 -> -1.3950366e+08 | F24: =+IFERROR((VLOOKUP((CONCATENATE($K$2,$F$9,$A24)),'[1]AÑO 2025'!$D:$I,6,0)),0)*-1 -> -91009550 | G24: =+E24-F24 -> -48494113 | H24: =IFERROR(G24/F24,0) -> 0.53284642
A25: 5135 | C25: =PROPER(+IFERROR(VLOOKUP(A25,'[1]AÑO 2025'!C:I,3,FALSE),0)) -> Gastos Servicios Administración | D25: 17 | E25: =+IFERROR((VLOOKUP((CONCATENATE($K$2,$E$9,$A25)),'[1]AÑO 2026'!$D:$I,6,0)),0)*-1 -> -3.5713966e+08 | F25: =+IFERROR((VLOOKUP((CONCATENATE($K$2,$F$9,$A25)),'[1]AÑO 2025'!$D:$I,6,0)),0)*-1 -> -2.5448915e+08 | G25: =+E25-F25 -> -1.026505e+08 | H25: =IFERROR(G25/F25,0) -> 0.40335905
A26: 5140 | C26: =PROPER(+IFERROR(VLOOKUP(A26,'[1]AÑO 2025'!C:I,3,FALSE),0)) -> Gastos Legales Administración | D26: 17 | E26: =+IFERROR((VLOOKUP((CONCATENATE($K$2,$E$9,$A26)),'[1]AÑO 2026'!$D:$I,6,0)),0)*-1 -> -9086208.2 | F26: =+IFERROR((VLOOKUP((CONCATENATE($K$2,$F$9,$A26)),'[1]AÑO 2025'!$D:$I,6,0)),0)*-1 -> -5839200.3 | G26: =+E26-F26 -> -3247007.9 | H26: =IFERROR(G26/F26,0) -> 0.55607065
A27: 5145 | C27: =PROPER(+IFERROR(VLOOKUP(A27,'[1]AÑO 2025'!C:I,3,FALSE),0)) -> Gastos Mantenimiento Administración | D27: 17 | E27: =+IFERROR((VLOOKUP((CONCATENATE($K$2,$E$9,$A27)),'[1]AÑO 2026'!$D:$I,6,0)),0)*-1 -> -3.0602756e+08 | F27: =+IFERROR((VLOOKUP((CONCATENATE($K$2,$F$9,$A27)),'[1]AÑO 2025'!$D:$I,6,0)),0)*-1 -> -1.7079617e+08 | G27: =+E27-F27 -> -1.3523139e+08 | H27: =IFERROR(G27/F27,0) -> 0.79177066
A28: 5150 | C28: =PROPER(+IFERROR(VLOOKUP(A28,'[1]AÑO 2025'!C:I,3,FALSE),0)) -> 0 | D28: 17 | E28: =+IFERROR((VLOOKUP((CONCATENATE($K$2,$E$9,$A28)),'[1]AÑO 2026'!$D:$I,6,0)),0)*-1 -> 0 | F28: =+IFERROR((VLOOKUP((CONCATENATE($K$2,$F$9,$A28)),'[1]AÑO 2025'!$D:$I,6,0)),0)*-1 -> 0 | G28: =+E28-F28 -> 0 | H28: =IFERROR(G28/F28,0) -> 0
A29: 5155 | C29: =PROPER(+IFERROR(VLOOKUP(A29,'[1]AÑO 2026'!C:I,3,FALSE),0)) -> Gastos De Viaje Administración | D29: 17 | E29: =+IFERROR((VLOOKUP((CONCATENATE($K$2,$E$9,$A29)),'[1]AÑO 2026'!$D:$I,6,0)),0)*-1 -> -828817.01 | F29: =+IFERROR((VLOOKUP((CONCATENATE($K$2,$F$9,$A29)),'[1]AÑO 2025'!$D:$I,6,0)),0)*-1 -> -810813 | G29: =+E29-F29 -> -18004.01 | H29: =IFERROR(G29/F29,0) -> 0.022204886
A30: 5160 | C30: =PROPER(+IFERROR(VLOOKUP(A30,'[1]AÑO 2025'!C:I,3,FALSE),0)) -> Gastos Depreciaciones Administración | D30: 17 | E30: =+IFERROR((VLOOKUP((CONCATENATE($K$2,$E$9,$A30)),'[1]AÑO 2026'!$D:$I,6,0)),0)*-1 -> -441338797 | F30: =+IFERROR((VLOOKUP((CONCATENATE($K$2,$F$9,$A30)),'[1]AÑO 2025'!$D:$I,6,0)),0)*-1 -> -249105084 | G30: =+E30-F30 -> -192233713 | H30: =IFERROR(G30/F30,0) -> 0.77169727
A31: 5165 | C31: =PROPER(+IFERROR(VLOOKUP(A31,'[1]AÑO 2025'!C:I,3,FALSE),0)) -> Amortizaciones | D31: 17 | E31: =+IFERROR((VLOOKUP((CONCATENATE($K$2,$E$9,$A31)),'[1]AÑO 2026'!$D:$I,6,0)),0)*-1 -> -66099803 | F31: =+IFERROR((VLOOKUP((CONCATENATE($K$2,$F$9,$A31)),'[1]AÑO 2025'!$D:$I,6,0)),0)*-1 -> -35191528 | G31: =+E31-F31 -> -30908275 | H31: =IFERROR(G31/F31,0) -> 0.87828739
A32: 5195 | C32: =PROPER(+IFERROR(VLOOKUP(A32,'[1]AÑO 2025'!C:I,3,FALSE),0)) -> Gastos Diversos Administración | D32: 17 | E32: =+IFERROR((VLOOKUP((CONCATENATE($K$2,$E$9,$A32)),'[1]AÑO 2026'!$D:$I,6,0)),0)*-1-100000 -> -2.0413889e+08 | F32: =+IFERROR((VLOOKUP((CONCATENATE($K$2,$F$9,$A32)),'[1]AÑO 2025'!$D:$I,6,0)),0)*-1 -> -52779625 | G32: =+E32-F32 -> -1.5135927e+08 | H32: =IFERROR(G32/F32,0) -> 2.8677594
A33: 5199 | C33: Gastos en cuentas de participación | D33: 17 | E33: =+IFERROR((VLOOKUP((CONCATENATE($K$3,$E$9,$A33)),'[1]AÑO 2026'!$D:$I,6,0)),0)*-1 -> 0 | F33: =+IFERROR((VLOOKUP((CONCATENATE($K$3,$F$9,$A33)),'[1]AÑO 2025'!$D:$I,6,0)),0) -> 0 | G33: =+E33-F33 -> 0 | H33: =IFERROR(G33/F33,0) -> 0
C34: Total gastos administrativos | E34: =+SUM(E19:E33) -> -3.6796646e+09 | F34: =+SUM(F19:F32)-F33 -> -2.4066547e+09 | G34: =+E34-F34 -> -1.2730098e+09 | H34: =IFERROR(G34/F34,0) -> 0.52895408
C35: GASTOS DE VENTAS
A36: 5205 | C36: =PROPER(+IFERROR(VLOOKUP(A36,'[1]AÑO 2025'!C:I,3,FALSE),0)) -> 0 | E36: =+IFERROR((VLOOKUP((CONCATENATE($K$3,$E$9,$A36)),'[1]AÑO 2026'!$D:$I,6,0)),0)*-1 -> 0 | F36: =+IFERROR((VLOOKUP((CONCATENATE($K$3,$F$9,$A36)),'[1]AÑO 2025'!$D:$I,6,0)),0)*-1 -> 0 | G36: =+E36-F36 -> 0 | H36: =IFERROR(G36/F36,0) -> 0
A37: 5210 | C37: =PROPER(+IFERROR(VLOOKUP(A37,'[1]AÑO 2025'!C:I,3,FALSE),0)) -> 0 | E37: =+IFERROR((VLOOKUP((CONCATENATE($K$3,$E$9,$A37)),'[1]AÑO 2026'!$D:$I,6,0)),0)*-1 -> 0 | F37: =+IFERROR((VLOOKUP((CONCATENATE($K$3,$F$9,$A37)),'[1]AÑO 2025'!$D:$I,6,0)),0)*-1 -> 0 | G37: =+E37-F37 -> 0 | H37: =IFERROR(G37/F37,0) -> 0
A38: 5215 | C38: =PROPER(+IFERROR(VLOOKUP(A38,'[1]AÑO 2025'!C:I,3,FALSE),0)) -> 0 | E38: =+IFERROR((VLOOKUP((CONCATENATE($K$3,$E$9,$A38)),'[1]AÑO 2026'!$D:$I,6,0)),0)*-1 -> 0 | F38: =+IFERROR((VLOOKUP((CONCATENATE($K$3,$F$9,$A38)),'[1]AÑO 2025'!$D:$I,6,0)),0)*-1 -> 0 | G38: =+E38-F38 -> 0 | H38: =IFERROR(G38/F38,0) -> 0
A39: 5220 | C39: =PROPER(+IFERROR(VLOOKUP(A39,'[1]AÑO 2025'!C:I,3,FALSE),0)) -> 0 | E39: =+IFERROR((VLOOKUP((CONCATENATE($K$3,$E$9,$A39)),'[1]AÑO 2026'!$D:$I,6,0)),0)*-1 -> 0 | F39: =+IFERROR((VLOOKUP((CONCATENATE($K$3,$F$9,$A39)),'[1]AÑO 2025'!$D:$I,6,0)),0)*-1 -> 0 | G39: =+E39-F39 -> 0 | H39: =IFERROR(G39/F39,0) -> 0
A40: 5225 | C40: =PROPER(+IFERROR(VLOOKUP(A40,'[1]AÑO 2025'!C:I,3,FALSE),0)) -> 0 | E40: =+IFERROR((VLOOKUP((CONCATENATE($K$3,$E$9,$A40)),'[1]AÑO 2026'!$D:$I,6,0)),0)*-1 -> 0 | F40: =+IFERROR((VLOOKUP((CONCATENATE($K$3,$F$9,$A40)),'[1]AÑO 2025'!$D:$I,6,0)),0)*-1 -> 0 | G40: =+E40-F40 -> 0 | H40: =IFERROR(G40/F40,0) -> 0
A41: 5230 | C41: =PROPER(+IFERROR(VLOOKUP(A41,'[1]AÑO 2025'!C:I,3,FALSE),0)) -> 0 | E41: =+IFERROR((VLOOKUP((CONCATENATE($K$3,$E$9,$A41)),'[1]AÑO 2026'!$D:$I,6,0)),0)*-1 -> 0 | F41: =+IFERROR((VLOOKUP((CONCATENATE($K$3,$F$9,$A41)),'[1]AÑO 2025'!$D:$I,6,0)),0)*-1 -> 0 | G41: =+E41-F41 -> 0 | H41: =IFERROR(G41/F41,0) -> 0
A42: 5235 | C42: =PROPER(+IFERROR(VLOOKUP(A42,'[1]AÑO 2025'!C:I,3,FALSE),0)) -> 0 | E42: =+IFERROR((VLOOKUP((CONCATENATE($K$3,$E$9,$A42)),'[1]AÑO 2026'!$D:$I,6,0)),0)*-1 -> 0 | F42: =+IFERROR((VLOOKUP((CONCATENATE($K$3,$F$9,$A42)),'[1]AÑO 2025'!$D:$I,6,0)),0)*-1 -> 0 | G42: =+E42-F42 -> 0 | H42: =IFERROR(G42/F42,0) -> 0
A43: 5240 | C43: =PROPER(+IFERROR(VLOOKUP(A43,'[1]AÑO 2025'!C:I,3,FALSE),0)) -> 0 | E43: =+IFERROR((VLOOKUP((CONCATENATE($K$3,$E$9,$A43)),'[1]AÑO 2026'!$D:$I,6,0)),0)*-1 -> 0 | F43: =+IFERROR((VLOOKUP((CONCATENATE($K$3,$F$9,$A43)),'[1]AÑO 2025'!$D:$I,6,0)),0)*-1 -> 0 | G43: =+E43-F43 -> 0 | H43: =IFERROR(G43/F43,0) -> 0
A44: 5245 | C44: =PROPER(+IFERROR(VLOOKUP(A44,'[1]AÑO 2025'!C:I,3,FALSE),0)) -> 0 | E44: =+IFERROR((VLOOKUP((CONCATENATE($K$3,$E$9,$A44)),'[1]AÑO 2026'!$D:$I,6,0)),0)*-1 -> 0 | F44: =+IFERROR((VLOOKUP((CONCATENATE($K$3,$F$9,$A44)),'[1]AÑO 2025'!$D:$I,6,0)),0)*-1 -> 0 | G44: =+E44-F44 -> 0 | H44: =IFERROR(G44/F44,0) -> 0
A45: 5250 | C45: =PROPER(+IFERROR(VLOOKUP(A45,'[1]AÑO 2025'!C:I,3,FALSE),0)) -> 0 | E45: =+IFERROR((VLOOKUP((CONCATENATE($K$3,$E$9,$A45)),'[1]AÑO 2026'!$D:$I,6,0)),0)*-1 -> 0 | F45: =+IFERROR((VLOOKUP((CONCATENATE($K$3,$F$9,$A45)),'[1]AÑO 2025'!$D:$I,6,0)),0)*-1 -> 0 | G45: =+E45-F45 -> 0 | H45: =IFERROR(G45/F45,0) -> 0
A46: 5255 | C46: =PROPER(+IFERROR(VLOOKUP(A46,'[1]AÑO 2026'!C:I,3,FALSE),0)) -> 0 | E46: =+IFERROR((VLOOKUP((CONCATENATE($K$3,$E$9,$A46)),'[1]AÑO 2026'!$D:$I,6,0)),0)*-1 -> 0 | F46: =+IFERROR((VLOOKUP((CONCATENATE($K$3,$F$9,$A46)),'[1]AÑO 2025'!$D:$I,6,0)),0)*-1 -> 0 | G46: =+E46-F46 -> 0 | H46: =IFERROR(G46/F46,0) -> 0
A47: 5260 | C47: =PROPER(+IFERROR(VLOOKUP(A47,'[1]AÑO 2026'!C:I,3,FALSE),0)) -> 0 | E47: =+IFERROR((VLOOKUP((CONCATENATE($K$3,$E$9,$A47)),'[1]AÑO 2026'!$D:$I,6,0)),0)*-1 -> 0 | F47: =+IFERROR((VLOOKUP((CONCATENATE($K$3,$F$9,$A47)),'[1]AÑO 2025'!$D:$I,6,0)),0)*-1 -> 0 | G47: =+E47-F47 -> 0 | H47: =IFERROR(G47/F47,0) -> 0
A48: 5265 | C48: =PROPER(+IFERROR(VLOOKUP(A48,'[1]AÑO 2026'!C:I,3,FALSE),0)) -> 0 | E48: =+IFERROR((VLOOKUP((CONCATENATE($K$3,$E$9,$A48)),'[1]AÑO 2026'!$D:$I,6,0)),0)*-1 -> 0 | F48: =+IFERROR((VLOOKUP((CONCATENATE($K$3,$F$9,$A48)),'[1]AÑO 2025'!$D:$I,6,0)),0)*-1 -> 0 | G48: =+E48-F48 -> 0 | H48: =IFERROR(G48/F48,0) -> 0
A49: 5295 | C49: =PROPER(+IFERROR(VLOOKUP(A49,'[1]AÑO 2025'!C:I,3,FALSE),0)) -> 0 | E49: =+IFERROR((VLOOKUP((CONCATENATE($K$3,$E$9,$A49)),'[1]AÑO 2026'!$D:$I,6,0)),0)*-1 -> 0 | F49: =+IFERROR((VLOOKUP((CONCATENATE($K$3,$F$9,$A49)),'[1]AÑO 2025'!$D:$I,6,0)),0)*-1 -> 0 | G49: =+E49-F49 -> 0 | H49: =IFERROR(G49/F49,0) -> 0
A50: 5299 | C50: =PROPER(+IFERROR(VLOOKUP(A50,'[1]AÑO 2025'!C:I,3,FALSE),0)) -> 0 | E50: =+IFERROR((VLOOKUP((CONCATENATE($K$3,$E$9,$A50)),'[1]AÑO 2026'!$D:$I,6,0)),0)*-1 -> 0 | F50: =+IFERROR((VLOOKUP((CONCATENATE($K$3,$F$9,$A50)),'[1]AÑO 2025'!$D:$I,6,0)),0)*-1 -> 0 | G50: =+E50-F50 -> 0 | H50: =IFERROR(G50/F50,0) -> 0
C51: Total gastos de ventas | E51: =+SUM(E36:E50) -> 0 | F51: =+SUM(F36:F50) -> 0 | G51: =+E51-F51 -> 0 | H51: =IFERROR(G51/F51,0) -> 0
C52: Utilidad operativa | E52: =+E16+E34+E51 -> 2.8446178e+08 | F52: =+F16+F34+F51 -> 8.2686313e+08 | G52: =+G16+G34+G51 -> -5.4240136e+08 | H52: =IFERROR(G52/F52,0) -> -0.65597477
E53: =+E52/E13 -> 0.026761756 | F53: =+F52/F13 -> 0.10536536 | G53: =+E53-F53 -> -0.078603602 | H53: =IFERROR(G53/F53,0) -> -0.74600992
C55: OTROS INGRESOS
A56: 4205 | C56: =PROPER(+IFERROR(VLOOKUP(A56,'[1]AÑO 2026'!C:I,3,FALSE),0)) -> 0 | E56: =+IFERROR((VLOOKUP((CONCATENATE($K$3,$E$9,$A56)),'[1]AÑO 2026'!$D:$I,6,0)),0)*-1 -> 0 | F56: =+IFERROR((VLOOKUP((CONCATENATE($K$3,$F$9,$A56)),'[1]AÑO 2025'!$D:$I,6,0)),0)*-1 -> 0 | G56: =+E56-F56 -> 0 | H56: =IFERROR(G56/F56,0) -> 0
A57: 4210 | C57: =PROPER(+IFERROR(VLOOKUP(A57,'[1]AÑO 2025'!C:I,3,FALSE),0)) -> Financieros | D57: 16 | E57: =+IFERROR((VLOOKUP((CONCATENATE($K$2,$E$9,$A57)),'[1]AÑO 2026'!$D:$I,6,0)),0)*-1 -> 13179908 | F57: =+IFERROR((VLOOKUP((CONCATENATE($K$2,$F$9,$A57)),'[1]AÑO 2025'!$D:$I,6,0)),0)*-1 -> 5609304 | G57: =+E57-F57 -> 7570604 | H57: =IFERROR(G57/F57,0) -> 1.3496512
A58: 4255 | C58: =PROPER(+IFERROR(VLOOKUP(A58,'[1]AÑO 2026'!C:I,3,FALSE),0)) -> Indemnizaciones | D58: 16 | E58: =+IFERROR((VLOOKUP((CONCATENATE($K$2,$E$9,$A58)),'[1]AÑO 2026'!$D:$I,6,0)),0)*-1 -> 1692542 | F58: =+IFERROR((VLOOKUP((CONCATENATE($K$2,$F$9,$A58)),'[1]AÑO 2025'!$D:$I,6,0)),0)*-1 -> 3161972 | G58: =+E58-F58 -> -1469430 | H58: =IFERROR(G58/F58,0) -> -0.46471949
A59: 4240 | C59: =PROPER(+IFERROR(VLOOKUP(A59,'[1]AÑO 2026'!C:I,3,FALSE),0)) -> 0 | D59: 16 | E59: =+IFERROR((VLOOKUP((CONCATENATE($K$2,$E$9,$A59)),'[1]AÑO 2026'!$D:$I,6,0)),0)*-1 -> 0 | F59: =+IFERROR((VLOOKUP((CONCATENATE($K$2,$F$9,$A59)),'[1]AÑO 2025'!$D:$I,6,0)),0)*-1 -> 0 | G59: =+E59-F59 -> 0 | H59: =IFERROR(G59/F59,0) -> 0
A60: 4250 | C60: =PROPER(+IFERROR(VLOOKUP(A60,'[1]AÑO 2026'!C:I,3,FALSE),0)) -> Recuperaciones Costos Y Gastos | D60: 16 | E60: =+IFERROR((VLOOKUP((CONCATENATE($K$2,$E$9,$A60)),'[1]AÑO 2026'!$D:$I,6,0)),0)*-1 -> 129731166 | F60: =+IFERROR((VLOOKUP((CONCATENATE($K$2,$F$9,$A60)),'[1]AÑO 2025'!$D:$I,6,0)),0)*-1 -> 86182315 | G60: =+E60-F60 -> 43548851 | H60: =IFERROR(G60/F60,0) -> 0.50531076
A61: 4295 | C61: Diversos | D61: 16 | E61: =+IFERROR((VLOOKUP((CONCATENATE($K$2,$E$9,$A61)),'[1]AÑO 2026'!$D:$I,6,0)),0)*-1 -> 334909.16 | F61: =+IFERROR((VLOOKUP((CONCATENATE($K$2,$F$9,$A61)),'[1]AÑO 2025'!$D:$I,6,0)),0)*-1 -> 2560914.8 | G61: =+E61-F61 -> -2226005.6 | H61: =IFERROR(G61/F61,0) -> -0.86922284
C62: Total otros ingresos | E62: =SUM(E56:E61) -> 1.4493853e+08 | F62: =SUM(F56:F61) -> 97514506 | G62: =+E62-F62 -> 47424019 | H62: =IFERROR(G62/F62,0) -> 0.48632784
C63: OTROS GASTOS
A64: 5305 | C64: =PROPER(+IFERROR(VLOOKUP(A64,'[1]AÑO 2025'!C:I,3,FALSE),0)) -> Gastos No Operacionales Financieros | D64: 18 | E64: =+IFERROR((VLOOKUP((CONCATENATE($K$2,$E$9,$A64)),'[1]AÑO 2026'!$D:$I,6,0)),0)*-1 -> -1.7192407e+08 | F64: =+IFERROR((VLOOKUP((CONCATENATE($K$2,$F$9,$A64)),'[1]AÑO 2025'!$D:$I,6,0)),0)*-1 -> -1.2938138e+08 | G64: =+E64-F64 -> -42542689 | H64: =IFERROR(G64/F64,0) -> 0.32881616
A65: 5315 | C65: =PROPER(+IFERROR(VLOOKUP(A65,'[1]AÑO 2025'!C:I,3,FALSE),0)) -> Gastos Extraordinarios | D65: 18 | E65: =+IFERROR((VLOOKUP((CONCATENATE($K$2,$E$9,$A65)),'[1]AÑO 2026'!$D:$I,6,0)),0)*-1 -> -2010 | F65: =+IFERROR((VLOOKUP((CONCATENATE($K$2,$F$9,$A65)),'[1]AÑO 2025'!$D:$I,6,0)),0)*-1 -> -216723.43 | G65: =+E65-F65 -> 214713.43 | H65: =IFERROR(G65/F65,0) -> -0.99072551
A66: 5395 | C66: =PROPER(+IFERROR(VLOOKUP(A66,'[1]AÑO 2025'!C:I,3,FALSE),0)) -> Gastos Diversos | D66: 18 | E66: =+IFERROR((VLOOKUP((CONCATENATE($K$2,$E$9,$A66)),'[1]AÑO 2026'!$D:$I,6,0)),0)*-1 -> -84263702 | F66: =+IFERROR((VLOOKUP((CONCATENATE($K$2,$F$9,$A66)),'[1]AÑO 2025'!$D:$I,6,0)),0)*-1 -> 165723.33 | G66: =+E66-F66 -> -84429425 | H66: =IFERROR(G66/F66,0) -> -509.4601
C67: Total otros gastos | E67: =SUM(E64:E66) -> -2.5618978e+08 | F67: =SUM(F64:F66) -> -1.2943238e+08 | G67: =+E67-F67 -> -1.267574e+08 | H67: =IFERROR(G67/F67,0) -> 0.97933299
C68: Utilidad antes de impuestos | E68: =+E52+E62+E67 -> 1.7321052e+08 | F68: =+F52+F62+F67 -> 7.9494526e+08 | G68: =+G52+G62+G67 -> -6.2173474e+08 | H68: =IFERROR(G68/F68,0) -> -0.78211013
A69: 54 | C69: Impuesto de renta y complementarios | D69: 19 | E69: =+IFERROR((VLOOKUP((CONCATENATE($K$2,$E$9,$A69)),'[1]AÑO 2026'!$D:$I,6,0)),0)*-1 -> -83326449 | F69: =+IFERROR((VLOOKUP((CONCATENATE($K$2,$F$9,$A69)),'[1]AÑO 2025'!$D:$I,6,0)),0)*-1 -> 0 | G69: =+E69-F69 -> -83326449 | H69: =IFERROR(G69/F69,0) -> 0
C70: UTILIDAD (PÉRDIDA) DEL PERÍODO | E70: =SUM(E68:E69) -> 89884071 | F70: =SUM(F68:F69) -> 7.9494526e+08 | G70: =SUM(G68:G69) -> -7.0506119e+08 | H70: =IFERROR(G70/F70,0) -> -0.88693049
C71: =+'2.ESF'!C53 -> Las notas son parte integral de los estados financieros individuales
C77: =+'2.ESF'!C59 -> MIGUEL ANTONIO JARAMILLO M | D77: ELIZABETH SOTO MEJIA | G77: =+'2.ESF'!G59 -> YURANY DEOSSA MURILLO
C78: =+'2.ESF'!C60 -> Representante Legal | D78: Revisor Fiscal | G78: =+'2.ESF'!G60 -> Contador Público
C79: =+'2.ESF'!C61 -> CC 80.550.424 | D79: Designado por TAX CONTADORES Y ABOGADOS S.A.S | G79: =+'2.ESF'!G61 -> TP 265026-T
C80: =+'2.ESF'!C62 -> (Ver Certificación Adjunta) | D80: TP 265041-T | G80: =+'2.ESF'!G62 -> (Ver Certificación Adjunta)
D81: (Ver Opinión Adjunta)

Sheet BALANCE POR TERCEROS 
B1: Libro Mayor
B2: OFTALMOLOGOS EL TESORO SAS 900755062-1
B3: Libro: LIBRO-BASE - Moneda: COP - Cuentas: Mayores e Imputables
B4: Periodos: Julio 2026 - Julio 2026
A6: Cuenta | B6: Nombre Cuenta | C6: Saldo Anterior | D6: Débito | E6: Crédito | F6: Neto | G6: Saldo Final
A7: 1 | B7: Activos | C7: 1.3698791e+10 | D7: 4.8735697e+09 | E7: 4.9152934e+09 | F7: -41723779 | G7: 1.3657067e+10
A8: 11 | B8: Efectivo y Equivalentes del Efectivo | C8: -1.7276078e+08 | D8: 1.8535466e+09 | E8: 1.6850003e+09 | F8: 1.6854623e+08 | G8: -4214553.1
A9: 1105 | B9: Caja | C9: 35922644 | D9: 309142862 | E9: 3.0601158e+08 | F9: 3131281.6 | G9: 39053925
A10: 110505 | B10: Caja General | C10: 60554 | D10: 2500000 | E10: 2161714 | F10: 338286 | G10: 398840
A11: 11050501 | B11: Caja menor OET | C11: 60554 | D11: 2500000 | E11: 2161714 | F11: 338286 | G11: 398840
A12: 110510 | B12: Cajas Menores | C12: 35862090 | D12: 306642862 | E12: 3.0384987e+08 | F12: 2792995.6 | G12: 38655085
A13: 11051001 | B13: Caja General | C13: 38897752 | D13: 245167650 | E13: 2.4237465e+08 | F13: 2792995.6 | G13: 41690748
A14: 11051003 | B14: Caja ajustes año 2021 | C14: 3537.8 | D14: 0 | E14: 0 | F14: 0 | G14: 3537.8
A15: 11051004 | B15: Caja cruce de cuentas | C15: -3039200 | D15: 61475212 | E15: 61475212 | F15: 0 | G15: -3039200
A16: 901216768 | B16: ADELANTE SOLUCIONES FINANCIERAS S.A.S. | C16: -386750 | D16: 0 | E16: 0 | F16: 0 | G16: -386750
A17: 22034122 | B17: ALIDIA DEL SOCORRO CANO AGUIRRE | C17: 5200000 | D17: 0 | E17: 0 | F17: 0 | G17: 5200000
A18: 1020458695 | B18: ALLISON ZAHIRA ARIAS LOPEZ | C18: 116025 | D18: 0 | E18: 0 | F18: 0 | G18: 116025
A19: 8392348 | B19: ANGEL DE JESUS GIL AVENDAÑO | C19: -700400 | D19: 0 | E19: 0 | F19: 0 | G19: -700400
A20: PA0898216 | B20: ANGEL JAVIER PAZ ARROCHA | C20: 150000 | D20: 0 | E20: 0 | F20: 0 | G20: 150000
A21: 1037637940 | B21: ANGIE SALOME ECHEVERRI CARMONA | C21: 78540 | D21: 0 | E21: 0 | F21: 0 | G21: 78540
A22: NY3942BC6 | B22: AZALIAH HAILEY CROES | C22: -409000 | D22: 0 | E22: 0 | F22: 0 | G22: -409000
A23: NY39442BC6 | B23: AZALIAH HAILEY CROES | C23: 409000 | D23: 0 | E23: 0 | F23: 0 | G23: 409000
A24: 901630573 | B24: BLACK MAMMOTH SURGICAL SAS | C24: -1964800 | D24: 0 | E24: 9197082 | F24: -9197082 | G24: -11161882
A25: 70554597 | B25: CARLOS ALBERTO RESTREPO AREIZA | C25: -6378000 | D25: 0 | E25: 0 | F25: 0 | G25: -6378000
A26: 2000012254 | B26: CAROLINA SARDI | C26: 801000 | D26: 0 | E26: 0 | F26: 0 | G26: 801000
A27: 44003672 | B27: CLAUDIA HENAO GARCIA | C27: -101000 | D27: 0 | E27: 0 | F27: 0 | G27: -101000
A28: 32444912 | B28: CONSUELO RESTREPO | C28: 53500 | D28: 0 | E28: 0 | F28: 0 | G28: 53500
A29: 1000088363 | B29: DARWIN ALEXANDER BUSTAMANTE MONTOYA | C29: 154700 | D29: 0 | E29: 0 | F29: 0 | G29: 154700
A30: 32227466 | B30: DIANA CRISTINA MIRA PATIÑO | C30: 1940000 | D30: 0 | E30: 0 | F30: 0 | G30: 1940000
A31: 42866008 | B31: DORALBA NARANJO HENAO | C31: 3489000 | D31: 0 | E31: 0 | F31: 0 | G31: 3489000
A32: 1037617376 | B32: ELIANA LONDOÑO CANO | C32: -1068400 | D32: 0 | E32: 0 | F32: 0 | G32: -1068400
A33: 1035870331 | B33: ELIANA MARCELA URQUIJO RAMIREZ | C33: 83300 | D33: 0 | E33: 0 | F33: 0 | G33: 83300
A34: 16585666 | B34: ELMER TORRES TORRES CASTRO | C34: -8064000 | D34: 0 | E34: 0 | F34: 0 | G34: -8064000
A35: 901503425 | B35: ESTRADA VANEGAS S.A.S. | C35: 101000 | D35: 0 | E35: 0 | F35: 0 | G35: 101000
... A62: 530962818 | B62: RICHARD DUENAS | C62: 420000 | D62: 0 | E62: 0 | F62: 0 | G62: 420000
A63: A80131390 | B63: RICHARD WILLIAM DUENAS | C63: -420000 | D63: 0 | E63: 0 | F63: 0 | G63: -420000
A64: 1000633916 | B64: SIMON FRANCO URIBE URIBE | C64: 165000 | D64: 0 | E64: 0 | F64: 0 | G64: 165000
A65: 1090388155 | B65: TATIANA HERNANDEZ SALAZAR | C65: 705800 | D65: 0 | E65: 0 | F65: 0 | G65: 705800
A66: 1120 | B66: Cuentas de Ahorro | C66: -2.0868342e+08 | D66: 1.5444037e+09 | E66: 1.3789888e+09 | F66: 1.6541494e+08 | G66: -43268479
A67: 112005 | B67: Bancos | C67: -2.0868342e+08 | D67: 1.5444037e+09 | E67: 1.3789888e+09 | F67: 1.6541494e+08 | G67: -43268479
A68: 11200501 | B68: Cuenta Bancolombia ahorros OET | C68: -1.4707765e+08 | D68: 112778507 | E68: 87405981 | F68: 25372526 | G68: -1.2170513e+08
A69: 11200502 | B69: Cuenta Bancolombia ahorros cuenta participación | C69: -61120893 | D69: 635855763 | E69: 583598577 | F69: 52257186 | G69: -8863706.5
A70: 11200503 | B70: Cuenta BBVA Ahorros OET | C70: 5712637 | D70: 0 | E70: 0 | F70: 0 | G70: 5712637
A71: 11200504 | B71: Cuenta Bancoomeva ahorros OET | C71: -53038331 | D71: 95728523 | E71: 50525774 | F71: 45202749 | G71: -7835582.5
A72: 11200505 | B72: CTA BANCO CAJA SOCIAL OET | C72: 36577495 | D72: 7.0004091e+08 | E72: 6.5744352e+08 | F72: 42597384 | G72: 79174879
A73: 11200506 | B73: Cuenta Bancolombia ahorros proyecto expansión | C73: 10263323 | D73: 0 | E73: 14900 | F73: -14900 | G73: 10248423
A74: 13 | B74: Cuentas por Cobrar | C74: 2.9266707e+09 | D74: 3.0000311e+09 | E74: 3.1530101e+09 | F74: -1.5297903e+08 | G74: 2.7736917e+09
A75: 1305 | B75: Clientes | C75: 1.4059259e+09 | D75: 2.6424153e+09 | E75: 2.7040573e+09 | F75: -61642001 | G75: 1.3442839e+09
... A147: 860027404 | B147: ALLIANZ SEGUROS DE VIDA SA | C147: 1.0451205e+08 | D147: 95811568 | E147: 1.458123e+08 | F147: -50000729 | G147: 54511317
A148: C29118367 | B148: ALMA NYDIA ALMAODOVAR | C148: 0 | D148: 21000000 | E148: 21000000 | F148: 0 | G148: 0
A149: 71757184 | B149: ALVARO ANDRES ZAPATA VELEZ | C149: -0.3 | D149: 0 | E149: 0 | F149: 0 | G149: -0.3
A150: 71626370 | B150: ALVARO CASAS SAMPEDRO | C150: 1 | D150: 0 | E150: 0 | F150: 0 | G150: 1
A151: 1128395842 | B151: ALVARO HELI MARIN DUQUE | C151: 0 | D151: 963000 | E151: 963000 | F151: 0 | G151: 0
A152: 8284880 | B152: ALVARO JARAMILLO JARAMILLO CARDENAS | C152: 0 | D152: 195600 | E152: 195600 | F152: 0 | G152: 0
A153: 3599402 | B153: ALVARO PIO VALENCIA VELEZ | C153: 0 | D153: 114400 | E153: 114400 | F153: 0 | G153: 0
A154: 79236999 | B154: ALVARO TAPIAS MILLAN | C154: 0 | D154: 60400 | E154: 60400 | F154: 0 | G154: 0
A155: 1126667015 | B155: ALWIN ALEXIS CROES ARAQUE | C155: 0 | D155: 326600 | E155: 326600 | F155: 0 | G155: 0
A156: 1035027132 | B156: AMALIA ARISTIZABAL GOMEZ | C156: 0 | D156: 82800 | E156: 82800 | F156: 0 | G156: 0
A157: 1035017821 | B157: AMALIA ECHAVARRIA CASTRO | C157: 0 | D157: 101800 | E157: 101800 | F157: 0 | G157: 0
A158: 43983660 | B158: AMALIA LOPEZ JARAMILLO | C158: 0 | D158: 101800 | E158: 101800 | F158: 0 | G158: 0
A159: 1035018665 | B159: AMALIA ORLANDO SUAREZ | C159: 0 | D159: 101800 | E159: 101800 | F159: 0 | G159: 0
A160: 1035013713 | B160: AMALIA ZULETA VALENCIA | C160: 0 | D160: 101800 | E160: 101800 | F160: 0 | G160: 0
... A226: 1053861574 | B226: ANGIE XIMENA ORTEGA PANTOJA | C226: 0 | D226: 9500000 | E226: 9500000 | F226: 0 | G226: 0
A227: RD6347727 | B227: ANNY LIDACEL CABRAL SALVADOR | C227: 1 | D227: 0 | E227: 0 | F227: 0 | G227: 1
A228: 1037587514 | B228: ANNY TATIANA ARROYAVE QUINTERO | C228: 0 | D228: 168200 | E228: 168200 | F228: 0 | G228: 0
A229: 1035016793 | B229: ANTHONY JARAMILLO OLAYA | C229: 0 | D229: 101800 | E229: 101800 | F229: 0 | G229: 0
A230: 1031943331 | B230: ANTHONY SAMUEL OCAMPO RÍOS | C230: 0 | D230: 76800 | E230: 76800 | F230: 0 | G230: 0
A231: 1034992360 | B231: ANTONIA AGUDELO JIMENEZ | C231: 0 | D231: 297000 | E231: 297000 | F231: 0 | G231: 0
A232: 1020236598 | B232: ANTONIA ARBOLEDA ORREGO | C232: 0 | D232: 101800 | E232: 101800 | F232: 0 | G232: 0
A233: 1035000513 | B233: ANTONIA CALLE CALLE VERGARA | C233: 0 | D233: 101800 | E233: 101800 | F233: 0 | G233: 0
A234: 1034991973 | B234: ANTONIA HINCAPIE VILLA | C234: 0 | D234: 73200 | E234: 73200 | F234: 0 | G234: 0
A235: 1022008441 | B235: ANTONIA LOPEZ LONDOÑO | C235: 0 | D235: 101800 | E235: 101800 | F235: 0 | G235: 0
A236: 1035005013 | B236: ANTONIA ROLDAN GALLEGO | C236: 0 | D236: 73200 | E236: 73200 | F236: 0 | G236: 0
A237: 21449741 | B237: ARELIS ALVAREZ ALVAREZ MUÑOZ | C237: 0 | D237: 319000 | E237: 319000 | F237: 0 | G237: 0
A238: 3468828 | B238: ARGEMIRO DE JESUS MUÑOZ URIBE | C238: 3 | D238: 0 | E238: 0 | F238: 0 | G238: 3
A239: 43265192 | B239: ARGENIS QUINTERO VALDERRAMA | C239: 0 | D239: 101800 | E239: 101800 | F239: 0 | G239: 0
... A254: 860002183 | B254: AXA COLPATRIA SEGUROS DE VIDA S.A. | C254: 4265829 | D254: 6138386 | E254: 2227823 | F254: 3910563 | G254: 8176392
A255: NX5L12J68 | B255: AYRIANA MARIA TJIN KON FAT | C255: 0 | D255: 580000 | E255: 580000 | F255: 0 | G255: 0
A256: 1219213434 | B256: AYSHA VILLAVERDE IZQUIERDO | C256: 1 | D256: 0 | E256: 0 | F256: 0 | G256: 1
A257: NY3942BC6 | B257: AZALIAH HAILEY CROES | C257: 0 | D257: 4300000 | E257: 4300000 | F257: 0 | G257: 0
A258: NY39442BC6 | B258: AZALIAH HAILEY CROES | C258: 0 | D258: 4300000 | E258: 4300000 | F258: 0 | G258: 0
A259: 42996677 | B259: BEATRIZ ELENA CASTAÑO RAMIREZ | C259: 0 | D259: 101800 | E259: 101800 | F259: 0 | G259: 0
A260: 43062123 | B260: BEATRIZ ELENA GARCIA CORRALES | C260: 2658000 | D260: 0 | E260: 2658000 | F260: -2658000 | G260: 0
A261: 21714188 | B261: BEATRIZ ELENA JIMENEZ PEREZ | C261: 0 | D261: 101800 | E261: 101800 | F261: 0 | G261: 0
A262: 42823737 | B262: BEATRIZ ELENA MEJIA VARELAS | C262: 0 | D262: 319000 | E262: 319000 | F262: 0 | G262: 0
A263: 1039679460 | B263: BEATRIZ ELENA URIBE ESCOBAR | C263: 0 | D263: 108400 | E263: 108400 | F263: 0 | G263: 0
A264: 42870992 | B264: BEATRIZ EUGENIA TORO PALACIO | C264: 0 | D264: 4900000 | E264: 4900000 | F264: 0 | G264: 0
A265: 52451625 | B265: BEATRIZ HELENA RODADO GRIJALBA | C265: 0 | D265: 101800 | E265: 101800 | F265: 0 | G265: 0
A266: 43110688 | B266: BEATRIZ LUCIA VELEZ ECHAVARRIA | C266: 0 | D266: 114400 | E266: 114400 | F266: 0 | G266: 0
A267: 42968835 | B267: BEATRIZ ZULEMA FORONDA MONTOYA | C267: 1 | D267: 0 | E267: 0 | F267: 0 | G267: 1
A268: 1022008778 | B268: BELEN LOPEZ LONDOÑO | C268: 0 | D268: 101800 | E268: 101800 | F268: 0 | G268: 0
A269: 22103904 | B269: BELEN VARELA VARELA RIVAS | C269: 0 | D269: 7310200 | E269: 7310200 | F269: 0 | G269: 0
A270: 43499791 | B270: BELLAIRE DEL PILAR OROZCO CASTRILLON | C270: 0 | D270: 297000 | E270: 297000 | F270: 0 | G270: 0
... A278: 901630573 | B278: BLACK MAMMOTH SURGICAL SAS | C278: 49969801 | D278: 16490082 | E278: 37980164 | F278: -21490082 | G278: 28479719
A279: A08407701 | B279: BLAIR FITTS PORTER | C279: 0 | D279: 382000 | E279: 382000 | F279: 0 | G279: 0
A280: 43475947 | B280: BLANCA CECILIA PEREZ AGUIRRE | C280: 0 | D280: 4551200 | E280: 4551200 | F280: 0 | G280: 0
A281: 43046008 | B281: BLANCA EUGENIA MONSALVE RUIZ | C281: 0 | D281: 223300 | E281: 223300 | F281: 0 | G281: 0
A282: 25062889 | B282: BLANCA FABIOLA GALLEGO RESTREPO | C282: 676000 | D282: 0 | E282: 676000 | F282: -676000 | G282: 0
A283: 42751453 | B283: BLANCA INES MONTOYA CARDONA | C283: 0 | D283: 193800 | E283: 193800 | F283: 0 | G283: 0
A284: 43746429 | B284: BLANCA JANNETH YEPES ALVAREZ | C284: 0 | D284: 3519200 | E284: 3519200 | F284: 0 | G284: 0
...
